lokus/__init__.py
lokus/__main__.py
lokus/cli.py
lokus/config_loader.py
lokus/deep_search.py
lokus/lgpd_validator.py
lokus/pdf_reporter.py
lokus/reporter.py
lokus/security_validator.py
lokus/yaml_parser.py
lokus-1.0.1.dist-info/licenses/LICENSE
lokus-1.0.1.dist-info/METADATA
lokus-1.0.1.dist-info/WHEEL
lokus-1.0.1.dist-info/entry_points.txt
lokus-1.0.1.dist-info/top_level.txt
lokus-1.0.1.dist-info/RECORD
