Metadata-Version: 2.4
Name: Lokus
Version: 1.0.1
Summary: Lokus: Find issues in your APIs from the docs
Author: Robson Damasceno, Virgílio Oliveira
Author-email: Vitor Cardoso <vitor.cardoso5@fatec.sp.gov.br>
Maintainer-email: Vitor Cardoso <vitor.cardoso5@fatec.sp.gov.br>
Keywords: security,lgpd,swagger,api,openapi
Requires-Python: >=3.8
License-File: LICENSE
Requires-Dist: click>=8.1.8
Requires-Dist: pydantic>=2.10.6
Requires-Dist: pyyaml>=6.0.2
Requires-Dist: reportlab>=4.4.1
Requires-Dist: svglib>=1.5.1
Dynamic: license-file
